Metadata-Version: 2.1
Name: pygifsicle
Version: 1.1.0
Summary: Python package wrapping the gifsicle library for editing and optimizing gifs.
Home-page: https://github.com/LucaCappelletti94/pygifsicle
Author: Luca Cappelletti
Author-email: cappelletti.luca94@gmail.com
License: MIT
Platform: UNKNOWN
Classifier: Development Status :: 5 - Production/Stable
Classifier: License :: OSI Approved :: MIT License
Classifier: Programming Language :: Python :: 3
Provides-Extra: test
License-File: LICENSE
